{
  "id": 17,
  "contest_type": "Referendum",
  "name": "Non-Citizen Voting in School Board, Measure N",
  "title": "Non-Citizen Voting in School Board, Measure N",
  "summary": null,
  "number": "N",
  "supporting_organizations": [
    {
      "id": null,
      "name": "Coalition for Immigrant Parent Empowerment, Yes on N, 2016",
      "payee": "Coalition for Immigrant Parent Empowerment, Yes on N, 2016",
      "amount": 15694.099999999999
    }
  ],
  "total_contributions": [

  ],
  "contributions_by_region": [

  ],
  "contributions_by_type": [

  ]
}
