{
  "iec": true,
  "total_contributions": 9072.94,
  "contributions": [
    {
      "date": "2016-11-08",
      "title": "Oakland November 8th, 2016 Election",
      "Cmte_ID": "1367599",
      "Filer_ID": "1380387",
      "Tran_Emp": null,
      "Tran_Occ": null,
      "Entity_Cd": "Committee",
      "Tran_Amt1": 8872.94,
      "Tran_Date": "2015-09-30",
      "Tran_NamF": null,
      "Tran_NamL": "Oakland Families for Quality Schools PAC",
      "Tran_Zip4": "95815",
      "election_name": "oakland-2016"
    },
    {
      "date": "2016-11-08",
      "title": "Oakland November 8th, 2016 Election",
      "Cmte_ID": null,
      "Filer_ID": "1380387",
      "Tran_Emp": "Leadership Public Schools",
      "Tran_Occ": "Educator",
      "Entity_Cd": "Individual",
      "Tran_Amt1": 200.0,
      "Tran_Date": "2016-05-04",
      "Tran_NamF": "Louise",
      "Tran_NamL": "Waters",
      "Tran_Zip4": "94587",
      "election_name": "oakland-2016"
    }
  ],
  "contributions_by_election": [
    [
      "2016-11-08",
      [
        "Oakland November 8th, 2016 Election",
        9072.94
      ]
    ]
  ]
}
